argali/__init__.py
argali/descriptive_statistics.py
argali/frequency.py
argali-0.1.8.dist-info/LICENSE
argali-0.1.8.dist-info/METADATA
argali-0.1.8.dist-info/WHEEL
argali-0.1.8.dist-info/top_level.txt
argali-0.1.8.dist-info/RECORD
