Metadata-Version: 2.1
Name: argali
Version: 0.1.8
Summary: Data Analysis Tools
Home-page: https://github.com/AaronHonour/argali
Author: Aaron Honour
Author-email: aaron_honour@protonmail.com
License: UNKNOWN
Platform: UNKNOWN
Classifier: Programming Language :: Python :: 3
Classifier: License :: OSI Approved :: MIT License
Classifier: Operating System :: OS Independent
Requires-Python: >=3.6
